ocsf_json_schema/__about__.py
ocsf_json_schema/__init__.py
ocsf_json_schema/embedded.py
ocsf_json_schema/loader.py
ocsf_json_schema/pickle_it.py
ocsf_json_schema/schema.py
ocsf_json_schema/utility.py
ocsf_json_schema/ocsf/1.0.0-rc.2.json
ocsf_json_schema/ocsf/1.0.0-rc.3.json
ocsf_json_schema/ocsf/1.0.0.json
ocsf_json_schema/ocsf/1.1.0.json
ocsf_json_schema/ocsf/1.2.0.json
ocsf_json_schema/ocsf/1.3.0.json
ocsf_json_schema/ocsf/1.4.0.json
ocsf_json_schema/ocsf/1.5.0.json
ocsf_json_schema/ocsf/1.6.0.json
ocsf_json_schema/ocsf/1.7.0.json
ocsf_json_schema/ocsf/LICENSE.txt
ocsf_json_schema/ocsf/README.md
ocsf_json_schema-1.1.0.dist-info/METADATA
ocsf_json_schema-1.1.0.dist-info/WHEEL
ocsf_json_schema-1.1.0.dist-info/licenses/LICENSE
ocsf_json_schema-1.1.0.dist-info/RECORD
