Metadata-Version: 2.4
Name: ocsf-json-schema
Version: 1.1.0
Summary: A Python library for generating OCSF JSON schemas.
Author-email: Neil Smith <neil@nsmith.net>
License-Expression: MIT
License-File: LICENSE
Requires-Python: >=3.10
